[
  {
    "id": 1750004094953,
    "login": "admin",
    "password": "$2b$10$YXYTWvxrgvnOCB3vrcljHOrUIlK5F49XKzQkV2BdSuG2bBe6bJzsm",
    "option": "light",
    "history": []
  },
  {
    "id": 1750004371282,
    "login": "dosia",
    "password": "$2b$10$gX9UMJYKbHgOBrhEdqLt0eds5rDBlT5B7CCdo8IkDebb/pUdJRuBq",
    "option": "light",
    "history": [
      {
        "data": "2025-06-17T14:29:46.313Z",
        "categories": [
          "Egzamin 2024"
        ],
        "list": [
          {
            "id_questions": 2562,
            "answer": "C",
            "correct": true
          },
          {
            "id_questions": 2614,
            "answer": "A",
            "correct": true
          },
          {
            "id_questions": 2577,
            "answer": "C",
            "correct": true
          },
          {
            "id_questions": 2500,
            "answer": "A",
            "correct": true
          },
          {
            "id_questions": 2516,
            "answer": "A",
            "correct": true
          },
          {
            "id_questions": 2616,
            "answer": "C",
            "correct": true
          },
          {
            "id_questions": 2564,
            "answer": "B",
            "correct": true
          },
          {
            "id_questions": 2538,
            "answer": "A",
            "correct": true
          },
          {
            "id_questions": 2546,
            "answer": "C",
            "correct": true
          },
          {
            "id_questions": 2574,
            "answer": "B",
            "correct": true
          },
          {
            "id_questions": 2508,
            "answer": "C",
            "correct": true
          },
          {
            "id_questions": 2550,
            "answer": "C",
            "correct": true
          },
          {
            "id_questions": 2520,
            "answer": "C",
            "correct": true
          },
          {
            "id_questions": 2626,
            "answer": "A",
            "correct": true
          },
          {
            "id_questions": 2555,
            "answer": "C",
            "correct": true
          },
          {
            "id_questions": 2594,
            "answer": "B",
            "correct": true
          },
          {
            "id_questions": 2608,
            "answer": "C",
            "correct": true
          },
          {
            "id_questions": 2593,
            "answer": "C",
            "correct": true
          },
          {
            "id_questions": 2603,
            "answer": "B",
            "correct": true
          },
          {
            "id_questions": 2579,
            "answer": "C",
            "correct": true
          },
          {
            "id_questions": 2521,
            "answer": "A",
            "correct": true
          },
          {
            "id_questions": 2618,
            "answer": "B",
            "correct": true
          },
          {
            "id_questions": 2531,
            "answer": "C",
            "correct": true
          },
          {
            "id_questions": 2572,
            "answer": "A",
            "correct": true
          },
          {
            "id_questions": 2623,
            "answer": "A",
            "correct": true
          },
          {
            "id_questions": 2502,
            "answer": "C",
            "correct": true
          },
          {
            "id_questions": 2591,
            "answer": "B",
            "correct": true
          },
          {
            "id_questions": 2590,
            "answer": "C",
            "correct": true
          },
          {
            "id_questions": 2615,
            "answer": "C",
            "correct": true
          },
          {
            "id_questions": 2634,
            "answer": "B",
            "correct": true
          },
          {
            "id_questions": 2527,
            "answer": "B",
            "correct": true
          },
          {
            "id_questions": 2633,
            "answer": "C",
            "correct": true
          },
          {
            "id_questions": 2558,
            "answer": "C",
            "correct": true
          },
          {
            "id_questions": 2605,
            "answer": "C",
            "correct": true
          },
          {
            "id_questions": 2584,
            "answer": "B",
            "correct": true
          },
          {
            "id_questions": 2632,
            "answer": "A",
            "correct": true
          },
          {
            "id_questions": 2619,
            "answer": "A",
            "correct": true
          },
          {
            "id_questions": 2585,
            "answer": "C",
            "correct": true
          },
          {
            "id_questions": 2545,
            "answer": "A",
            "correct": true
          },
          {
            "id_questions": 2528,
            "answer": "A",
            "correct": true
          },
          {
            "id_questions": 2611,
            "answer": "A",
            "correct": true
          },
          {
            "id_questions": 2540,
            "answer": "A",
            "correct": true
          },
          {
            "id_questions": 2573,
            "answer": "C",
            "correct": true
          },
          {
            "id_questions": 2565,
            "answer": "B",
            "correct": true
          },
          {
            "id_questions": 2583,
            "answer": "A",
            "correct": true
          },
          {
            "id_questions": 2553,
            "answer": "A",
            "correct": true
          },
          {
            "id_questions": 2542,
            "answer": "B",
            "correct": true
          },
          {
            "id_questions": 2499,
            "answer": "A",
            "correct": true
          },
          {
            "id_questions": 2580,
            "answer": "C",
            "correct": true
          },
          {
            "id_questions": 2638,
            "answer": "B",
            "correct": true
          },
          {
            "id_questions": 2570,
            "answer": "A",
            "correct": true
          },
          {
            "id_questions": 2575,
            "answer": "C",
            "correct": true
          },
          {
            "id_questions": 2620,
            "answer": "A",
            "correct": true
          },
          {
            "id_questions": 2506,
            "answer": "B",
            "correct": true
          },
          {
            "id_questions": 2563,
            "answer": "B",
            "correct": true
          },
          {
            "id_questions": 2571,
            "answer": "A",
            "correct": true
          },
          {
            "id_questions": 2599,
            "answer": "A",
            "correct": true
          },
          {
            "id_questions": 2587,
            "answer": "B",
            "correct": true
          },
          {
            "id_questions": 2600,
            "answer": "B",
            "correct": true
          },
          {
            "id_questions": 2495,
            "answer": "B",
            "correct": true
          },
          {
            "id_questions": 2522,
            "answer": "C",
            "correct": true
          },
          {
            "id_questions": 2629,
            "answer": "A",
            "correct": true
          },
          {
            "id_questions": 2625,
            "answer": "C",
            "correct": true
          },
          {
            "id_questions": 2613,
            "answer": "B",
            "correct": true
          },
          {
            "id_questions": 2612,
            "answer": "A",
            "correct": true
          },
          {
            "id_questions": 2637,
            "answer": "B",
            "correct": true
          },
          {
            "id_questions": 2512,
            "answer": "C",
            "correct": true
          },
          {
            "id_questions": 2497,
            "answer": "C",
            "correct": true
          },
          {
            "id_questions": 2595,
            "answer": "B",
            "correct": true
          },
          {
            "id_questions": 2601,
            "answer": "C",
            "correct": true
          },
          {
            "id_questions": 2552,
            "answer": "C",
            "correct": true
          },
          {
            "id_questions": 2624,
            "answer": "C",
            "correct": true
          },
          {
            "id_questions": 2536,
            "answer": "B",
            "correct": true
          },
          {
            "id_questions": 2598,
            "answer": "A",
            "correct": true
          },
          {
            "id_questions": 2581,
            "answer": "B",
            "correct": true
          },
          {
            "id_questions": 2631,
            "answer": "C",
            "correct": true
          },
          {
            "id_questions": 2498,
            "answer": "C",
            "correct": true
          },
          {
            "id_questions": 2627,
            "answer": "C",
            "correct": true
          },
          {
            "id_questions": 2610,
            "answer": "A",
            "correct": true
          },
          {
            "id_questions": 2568,
            "answer": "B",
            "correct": true
          },
          {
            "id_questions": 2530,
            "answer": "C",
            "correct": true
          },
          {
            "id_questions": 2566,
            "answer": "C",
            "correct": true
          },
          {
            "id_questions": 2592,
            "answer": "B",
            "correct": true
          },
          {
            "id_questions": 2556,
            "answer": "C",
            "correct": true
          },
          {
            "id_questions": 2639,
            "answer": "C",
            "correct": true
          },
          {
            "id_questions": 2567,
            "answer": "A",
            "correct": true
          },
          {
            "id_questions": 2534,
            "answer": "B",
            "correct": true
          },
          {
            "id_questions": 2609,
            "answer": "B",
            "correct": true
          },
          {
            "id_questions": 2496,
            "answer": "C",
            "correct": true
          },
          {
            "id_questions": 2515,
            "answer": "C",
            "correct": true
          },
          {
            "id_questions": 2505,
            "answer": "A",
            "correct": true
          },
          {
            "id_questions": 2628,
            "answer": "B",
            "correct": true
          },
          {
            "id_questions": 2630,
            "answer": "A",
            "correct": true
          },
          {
            "id_questions": 2509,
            "answer": "B",
            "correct": true
          },
          {
            "id_questions": 2569,
            "answer": "B",
            "correct": true
          },
          {
            "id_questions": 2557,
            "answer": "B",
            "correct": true
          },
          {
            "id_questions": 2544,
            "answer": "A",
            "correct": true
          },
          {
            "id_questions": 2525,
            "answer": "B",
            "correct": true
          },
          {
            "id_questions": 2533,
            "answer": "A",
            "correct": true
          },
          {
            "id_questions": 2607,
            "answer": "A",
            "correct": true
          },
          {
            "id_questions": 2596,
            "answer": "B",
            "correct": true
          },
          {
            "id_questions": 2578,
            "answer": "A",
            "correct": true
          },
          {
            "id_questions": 2606,
            "answer": "B",
            "correct": true
          },
          {
            "id_questions": 2529,
            "answer": "A",
            "correct": true
          },
          {
            "id_questions": 2511,
            "answer": "A",
            "correct": true
          },
          {
            "id_questions": 2514,
            "answer": "B",
            "correct": true
          },
          {
            "id_questions": 2513,
            "answer": "A",
            "correct": true
          },
          {
            "id_questions": 2504,
            "answer": "A",
            "correct": true
          },
          {
            "id_questions": 2526,
            "answer": "A",
            "correct": true
          },
          {
            "id_questions": 2501,
            "answer": "B",
            "correct": true
          },
          {
            "id_questions": 2551,
            "answer": "A",
            "correct": true
          },
          {
            "id_questions": 2586,
            "answer": "C",
            "correct": true
          },
          {
            "id_questions": 2510,
            "answer": "B",
            "correct": true
          },
          {
            "id_questions": 2560,
            "answer": "B",
            "correct": true
          },
          {
            "id_questions": 2621,
            "answer": "B",
            "correct": true
          },
          {
            "id_questions": 2576,
            "answer": "B",
            "correct": true
          },
          {
            "id_questions": 2519,
            "answer": "B",
            "correct": true
          },
          {
            "id_questions": 2547,
            "answer": "C",
            "correct": true
          },
          {
            "id_questions": 2554,
            "answer": "C",
            "correct": true
          },
          {
            "id_questions": 2559,
            "answer": "A",
            "correct": true
          },
          {
            "id_questions": 2561,
            "answer": "B",
            "correct": true
          },
          {
            "id_questions": 2597,
            "answer": "B",
            "correct": true
          },
          {
            "id_questions": 2604,
            "answer": "B",
            "correct": true
          },
          {
            "id_questions": 2622,
            "answer": "C",
            "correct": true
          },
          {
            "id_questions": 2617,
            "answer": "B",
            "correct": true
          },
          {
            "id_questions": 2507,
            "answer": "C",
            "correct": true
          },
          {
            "id_questions": 2549,
            "answer": "A",
            "correct": true
          },
          {
            "id_questions": 2537,
            "answer": "A",
            "correct": true
          },
          {
            "id_questions": 2503,
            "answer": "B",
            "correct": true
          },
          {
            "id_questions": 2539,
            "answer": "A",
            "correct": true
          },
          {
            "id_questions": 2524,
            "answer": "B",
            "correct": true
          },
          {
            "id_questions": 2517,
            "answer": "B",
            "correct": true
          },
          {
            "id_questions": 2541,
            "answer": "A",
            "correct": true
          },
          {
            "id_questions": 2535,
            "answer": "A",
            "correct": true
          },
          {
            "id_questions": 2589,
            "answer": "A",
            "correct": true
          },
          {
            "id_questions": 2636,
            "answer": "A",
            "correct": true
          },
          {
            "id_questions": 2518,
            "answer": "A",
            "correct": true
          },
          {
            "id_questions": 2543,
            "answer": "B",
            "correct": true
          },
          {
            "id_questions": 2582,
            "answer": "C",
            "correct": true
          },
          {
            "id_questions": 2635,
            "answer": "C",
            "correct": true
          },
          {
            "id_questions": 2602,
            "answer": "A",
            "correct": true
          },
          {
            "id_questions": 2588,
            "answer": "C",
            "correct": true
          },
          {
            "id_questions": 2523,
            "answer": "C",
            "correct": true
          },
          {
            "id_questions": 2548,
            "answer": "B",
            "correct": true
          },
          {
            "id_questions": 2532,
            "answer": "C",
            "correct": true
          }
        ],
        "correct": 145,
        "wrong": 0,
        "type": "quiz"
      },
      {
        "data": "2025-06-17T15:47:18.974Z",
        "categories": [
          "Egzamin 2022"
        ],
        "list": [
          {
            "id_questions": 2271,
            "answer": "B",
            "correct": true
          },
          {
            "id_questions": 2261,
            "answer": "B",
            "correct": true
          },
          {
            "id_questions": 2336,
            "answer": "A",
            "correct": true
          },
          {
            "id_questions": 2263,
            "answer": "C",
            "correct": true
          },
          {
            "id_questions": 2267,
            "answer": "A",
            "correct": true
          },
          {
            "id_questions": 2330,
            "answer": "A",
            "correct": true
          },
          {
            "id_questions": 2344,
            "answer": "A",
            "correct": true
          },
          {
            "id_questions": 2242,
            "answer": "A",
            "correct": true
          },
          {
            "id_questions": 2318,
            "answer": "A",
            "correct": true
          },
          {
            "id_questions": 2245,
            "answer": "A",
            "correct": true
          },
          {
            "id_questions": 2338,
            "answer": "B",
            "correct": true
          },
          {
            "id_questions": 2346,
            "answer": "C",
            "correct": true
          },
          {
            "id_questions": 2294,
            "answer": "A",
            "correct": true
          },
          {
            "id_questions": 2219,
            "answer": "C",
            "correct": true
          },
          {
            "id_questions": 2262,
            "answer": "C",
            "correct": true
          },
          {
            "id_questions": 2297,
            "answer": "B",
            "correct": true
          },
          {
            "id_questions": 2270,
            "answer": "C",
            "correct": true
          },
          {
            "id_questions": 2282,
            "answer": "B",
            "correct": true
          },
          {
            "id_questions": 2310,
            "answer": "B",
            "correct": false
          },
          {
            "id_questions": 2343,
            "answer": "C",
            "correct": true
          },
          {
            "id_questions": 2293,
            "answer": "B",
            "correct": true
          },
          {
            "id_questions": 2265,
            "answer": "B",
            "correct": true
          },
          {
            "id_questions": 2213,
            "answer": "A",
            "correct": true
          },
          {
            "id_questions": 2231,
            "answer": "C",
            "correct": true
          },
          {
            "id_questions": 2222,
            "answer": "C",
            "correct": true
          },
          {
            "id_questions": 2244,
            "answer": "B",
            "correct": true
          },
          {
            "id_questions": 2229,
            "answer": "B",
            "correct": true
          },
          {
            "id_questions": 2216,
            "answer": "C",
            "correct": true
          },
          {
            "id_questions": 2308,
            "answer": "B",
            "correct": true
          },
          {
            "id_questions": 2272,
            "answer": "B",
            "correct": true
          },
          {
            "id_questions": 2207,
            "answer": "A",
            "correct": true
          },
          {
            "id_questions": 2306,
            "answer": "A",
            "correct": true
          },
          {
            "id_questions": 2238,
            "answer": "B",
            "correct": true
          },
          {
            "id_questions": 2342,
            "answer": "D",
            "correct": false
          },
          {
            "id_questions": 2215,
            "answer": "C",
            "correct": true
          },
          {
            "id_questions": 2305,
            "answer": "B",
            "correct": true
          },
          {
            "id_questions": 2269,
            "answer": "B",
            "correct": true
          },
          {
            "id_questions": 2217,
            "answer": "B",
            "correct": true
          },
          {
            "id_questions": 2302,
            "answer": "A",
            "correct": true
          },
          {
            "id_questions": 2317,
            "answer": "C",
            "correct": true
          },
          {
            "id_questions": 2289,
            "answer": "A",
            "correct": true
          },
          {
            "id_questions": 2307,
            "answer": "A",
            "correct": true
          },
          {
            "id_questions": 2345,
            "answer": "C",
            "correct": true
          },
          {
            "id_questions": 2224,
            "answer": "B",
            "correct": true
          },
          {
            "id_questions": 2232,
            "answer": "C",
            "correct": true
          },
          {
            "id_questions": 2211,
            "answer": "C",
            "correct": true
          },
          {
            "id_questions": 2314,
            "answer": "C",
            "correct": true
          },
          {
            "id_questions": 2253,
            "answer": "B",
            "correct": true
          },
          {
            "id_questions": 2220,
            "answer": "B",
            "correct": true
          },
          {
            "id_questions": 2337,
            "answer": "C",
            "correct": true
          },
          {
            "id_questions": 2243,
            "answer": "A",
            "correct": true
          },
          {
            "id_questions": 2348,
            "answer": "C",
            "correct": true
          },
          {
            "id_questions": 2258,
            "answer": "C",
            "correct": true
          },
          {
            "id_questions": 2206,
            "answer": "C",
            "correct": true
          },
          {
            "id_questions": 2254,
            "answer": "C",
            "correct": true
          },
          {
            "id_questions": 2208,
            "answer": "B",
            "correct": true
          },
          {
            "id_questions": 2259,
            "answer": "A",
            "correct": true
          },
          {
            "id_questions": 2274,
            "answer": "B",
            "correct": true
          },
          {
            "id_questions": 2264,
            "answer": "A",
            "correct": true
          },
          {
            "id_questions": 2250,
            "answer": "B",
            "correct": true
          },
          {
            "id_questions": 2241,
            "answer": "B",
            "correct": false
          },
          {
            "id_questions": 2296,
            "answer": "B",
            "correct": true
          },
          {
            "id_questions": 2246,
            "answer": "B",
            "correct": true
          },
          {
            "id_questions": 2288,
            "answer": "C",
            "correct": true
          },
          {
            "id_questions": 2347,
            "answer": "B",
            "correct": true
          },
          {
            "id_questions": 2277,
            "answer": "B",
            "correct": true
          },
          {
            "id_questions": 2323,
            "answer": "B",
            "correct": true
          },
          {
            "id_questions": 2230,
            "answer": "B",
            "correct": true
          },
          {
            "id_questions": 2251,
            "answer": "B",
            "correct": true
          },
          {
            "id_questions": 2281,
            "answer": "A",
            "correct": true
          },
          {
            "id_questions": 2266,
            "answer": "B",
            "correct": true
          },
          {
            "id_questions": 2311,
            "answer": "A",
            "correct": true
          },
          {
            "id_questions": 2209,
            "answer": "A",
            "correct": true
          },
          {
            "id_questions": 2326,
            "answer": "B",
            "correct": true
          },
          {
            "id_questions": 2328,
            "answer": "B",
            "correct": true
          },
          {
            "id_questions": 2334,
            "answer": "C",
            "correct": true
          },
          {
            "id_questions": 2240,
            "answer": "C",
            "correct": true
          },
          {
            "id_questions": 2322,
            "answer": "C",
            "correct": true
          },
          {
            "id_questions": 2321,
            "answer": "C",
            "correct": true
          },
          {
            "id_questions": 2300,
            "answer": "A",
            "correct": true
          },
          {
            "id_questions": 2290,
            "answer": "B",
            "correct": true
          },
          {
            "id_questions": 2212,
            "answer": "C",
            "correct": true
          },
          {
            "id_questions": 2301,
            "answer": "A",
            "correct": true
          },
          {
            "id_questions": 2257,
            "answer": "A",
            "correct": true
          },
          {
            "id_questions": 2279,
            "answer": "A",
            "correct": true
          },
          {
            "id_questions": 2249,
            "answer": "B",
            "correct": true
          },
          {
            "id_questions": 2304,
            "answer": "C",
            "correct": true
          },
          {
            "id_questions": 2339,
            "answer": "C",
            "correct": true
          },
          {
            "id_questions": 2236,
            "answer": "A",
            "correct": true
          },
          {
            "id_questions": 2226,
            "answer": "A",
            "correct": true
          },
          {
            "id_questions": 2333,
            "answer": "B",
            "correct": true
          },
          {
            "id_questions": 2248,
            "answer": "A",
            "correct": true
          },
          {
            "id_questions": 2223,
            "answer": "A",
            "correct": true
          },
          {
            "id_questions": 2313,
            "answer": "A",
            "correct": true
          },
          {
            "id_questions": 2233,
            "answer": "C",
            "correct": true
          },
          {
            "id_questions": 2237,
            "answer": "C",
            "correct": true
          },
          {
            "id_questions": 2225,
            "answer": "B",
            "correct": false
          },
          {
            "id_questions": 2298,
            "answer": "A",
            "correct": true
          },
          {
            "id_questions": 2325,
            "answer": "C",
            "correct": true
          },
          {
            "id_questions": 2256,
            "answer": "B",
            "correct": true
          },
          {
            "id_questions": 2234,
            "answer": "A",
            "correct": true
          },
          {
            "id_questions": 2228,
            "answer": "C",
            "correct": true
          },
          {
            "id_questions": 2275,
            "answer": "B",
            "correct": true
          },
          {
            "id_questions": 2255,
            "answer": "A",
            "correct": true
          },
          {
            "id_questions": 2214,
            "answer": "C",
            "correct": true
          },
          {
            "id_questions": 2247,
            "answer": "C",
            "correct": true
          },
          {
            "id_questions": 2280,
            "answer": "A",
            "correct": true
          },
          {
            "id_questions": 2278,
            "answer": "C",
            "correct": true
          },
          {
            "id_questions": 2205,
            "answer": "A",
            "correct": true
          },
          {
            "id_questions": 2227,
            "answer": "C",
            "correct": true
          },
          {
            "id_questions": 2268,
            "answer": "C",
            "correct": true
          },
          {
            "id_questions": 2221,
            "answer": "A",
            "correct": true
          },
          {
            "id_questions": 2239,
            "answer": "C",
            "correct": true
          },
          {
            "id_questions": 2324,
            "answer": "A",
            "correct": true
          },
          {
            "id_questions": 2303,
            "answer": "B",
            "correct": true
          },
          {
            "id_questions": 2312,
            "answer": "B",
            "correct": true
          },
          {
            "id_questions": 2276,
            "answer": "B",
            "correct": true
          },
          {
            "id_questions": 2235,
            "answer": "B",
            "correct": true
          },
          {
            "id_questions": 2283,
            "answer": "A",
            "correct": true
          },
          {
            "id_questions": 2327,
            "answer": "A",
            "correct": true
          },
          {
            "id_questions": 2295,
            "answer": "A",
            "correct": true
          },
          {
            "id_questions": 2273,
            "answer": "C",
            "correct": true
          },
          {
            "id_questions": 2286,
            "answer": "C",
            "correct": true
          },
          {
            "id_questions": 2335,
            "answer": "C",
            "correct": true
          },
          {
            "id_questions": 2287,
            "answer": "A",
            "correct": true
          },
          {
            "id_questions": 2341,
            "answer": "B",
            "correct": true
          },
          {
            "id_questions": 2340,
            "answer": "B",
            "correct": true
          },
          {
            "id_questions": 2309,
            "answer": "A",
            "correct": true
          },
          {
            "id_questions": 2319,
            "answer": "C",
            "correct": true
          },
          {
            "id_questions": 2284,
            "answer": "C",
            "correct": false
          },
          {
            "id_questions": 2292,
            "answer": "C",
            "correct": true
          },
          {
            "id_questions": 2291,
            "answer": "C",
            "correct": true
          },
          {
            "id_questions": 2315,
            "answer": "C",
            "correct": true
          },
          {
            "id_questions": 2299,
            "answer": "B",
            "correct": true
          },
          {
            "id_questions": 2316,
            "answer": "A",
            "correct": true
          },
          {
            "id_questions": 2260,
            "answer": "B",
            "correct": true
          },
          {
            "id_questions": 2329,
            "answer": "B",
            "correct": true
          },
          {
            "id_questions": 2210,
            "answer": "C",
            "correct": true
          },
          {
            "id_questions": 2332,
            "answer": "A",
            "correct": true
          },
          {
            "id_questions": 2285,
            "answer": "C",
            "correct": true
          },
          {
            "id_questions": 2218,
            "answer": "B",
            "correct": true
          },
          {
            "id_questions": 2252,
            "answer": "B",
            "correct": true
          },
          {
            "id_questions": 2320,
            "answer": "A",
            "correct": true
          },
          {
            "id_questions": 2331,
            "answer": "C",
            "correct": true
          }
        ],
        "correct": 139,
        "wrong": 5,
        "type": "quiz"
      },
      {
        "data": "2025-06-17T15:47:59.300Z",
        "categories": [
          "Egzamin 2022"
        ],
        "list": [
          {
            "id_questions": 2310,
            "answer": "A",
            "correct": true
          },
          {
            "id_questions": 2342,
            "answer": "C",
            "correct": true
          },
          {
            "id_questions": 2241,
            "answer": "A",
            "correct": true
          },
          {
            "id_questions": 2225,
            "answer": "C",
            "correct": true
          },
          {
            "id_questions": 2284,
            "answer": "B",
            "correct": true
          }
        ],
        "correct": 5,
        "wrong": 0,
        "type": "Quiz - poprawa błędów"
      },
      {
        "data": "2025-06-17T16:20:22.518Z",
        "categories": [
          "Egzamin 2021"
        ],
        "list": [
          {
            "id_questions": 2126,
            "answer": "A",
            "correct": true
          },
          {
            "id_questions": 2096,
            "answer": "A",
            "correct": true
          },
          {
            "id_questions": 2152,
            "answer": "B",
            "correct": true
          },
          {
            "id_questions": 2102,
            "answer": "A",
            "correct": true
          },
          {
            "id_questions": 2202,
            "answer": "C",
            "correct": true
          },
          {
            "id_questions": 2172,
            "answer": "C",
            "correct": true
          },
          {
            "id_questions": 2120,
            "answer": "C",
            "correct": true
          },
          {
            "id_questions": 2084,
            "answer": "C",
            "correct": true
          },
          {
            "id_questions": 2114,
            "answer": "C",
            "correct": true
          },
          {
            "id_questions": 2196,
            "answer": "A",
            "correct": false
          },
          {
            "id_questions": 2117,
            "answer": "A",
            "correct": true
          },
          {
            "id_questions": 2130,
            "answer": "A",
            "correct": true
          },
          {
            "id_questions": 2161,
            "answer": "A",
            "correct": true
          },
          {
            "id_questions": 2198,
            "answer": "A",
            "correct": true
          },
          {
            "id_questions": 2085,
            "answer": "B",
            "correct": true
          },
          {
            "id_questions": 2118,
            "answer": "B",
            "correct": true
          },
          {
            "id_questions": 2180,
            "answer": "C",
            "correct": true
          },
          {
            "id_questions": 2181,
            "answer": "C",
            "correct": true
          },
          {
            "id_questions": 2133,
            "answer": "C",
            "correct": true
          },
          {
            "id_questions": 2077,
            "answer": "C",
            "correct": true
          },
          {
            "id_questions": 2144,
            "answer": "B",
            "correct": false
          },
          {
            "id_questions": 2159,
            "answer": "C",
            "correct": true
          },
          {
            "id_questions": 2122,
            "answer": "B",
            "correct": true
          },
          {
            "id_questions": 2165,
            "answer": "B",
            "correct": true
          },
          {
            "id_questions": 2093,
            "answer": "C",
            "correct": true
          },
          {
            "id_questions": 2123,
            "answer": "B",
            "correct": true
          },
          {
            "id_questions": 2153,
            "answer": "C",
            "correct": true
          },
          {
            "id_questions": 2119,
            "answer": "A",
            "correct": true
          },
          {
            "id_questions": 2091,
            "answer": "B",
            "correct": true
          },
          {
            "id_questions": 2108,
            "answer": "A",
            "correct": true
          },
          {
            "id_questions": 2170,
            "answer": "B",
            "correct": true
          },
          {
            "id_questions": 2156,
            "answer": "B",
            "correct": true
          },
          {
            "id_questions": 2164,
            "answer": "B",
            "correct": true
          },
          {
            "id_questions": 2106,
            "answer": "A",
            "correct": true
          },
          {
            "id_questions": 2125,
            "answer": "B",
            "correct": true
          },
          {
            "id_questions": 2166,
            "answer": "A",
            "correct": true
          },
          {
            "id_questions": 2115,
            "answer": "B",
            "correct": true
          },
          {
            "id_questions": 2173,
            "answer": "C",
            "correct": true
          },
          {
            "id_questions": 2190,
            "answer": "C",
            "correct": true
          },
          {
            "id_questions": 2141,
            "answer": "C",
            "correct": true
          },
          {
            "id_questions": 2143,
            "answer": "C",
            "correct": true
          },
          {
            "id_questions": 2160,
            "answer": "A",
            "correct": true
          },
          {
            "id_questions": 2087,
            "answer": "C",
            "correct": false
          },
          {
            "id_questions": 2195,
            "answer": "A",
            "correct": true
          },
          {
            "id_questions": 2145,
            "answer": "A",
            "correct": true
          },
          {
            "id_questions": 2097,
            "answer": "C",
            "correct": true
          },
          {
            "id_questions": 2098,
            "answer": "A",
            "correct": true
          },
          {
            "id_questions": 2184,
            "answer": "B",
            "correct": true
          },
          {
            "id_questions": 2132,
            "answer": "C",
            "correct": true
          },
          {
            "id_questions": 2187,
            "answer": "C",
            "correct": true
          },
          {
            "id_questions": 2064,
            "answer": "B",
            "correct": true
          },
          {
            "id_questions": 2157,
            "answer": "B",
            "correct": true
          },
          {
            "id_questions": 2193,
            "answer": "A",
            "correct": true
          },
          {
            "id_questions": 2065,
            "answer": "B",
            "correct": true
          },
          {
            "id_questions": 2149,
            "answer": "B",
            "correct": true
          },
          {
            "id_questions": 2100,
            "answer": "C",
            "correct": true
          },
          {
            "id_questions": 2147,
            "answer": "C",
            "correct": true
          },
          {
            "id_questions": 2063,
            "answer": "C",
            "correct": true
          },
          {
            "id_questions": 2151,
            "answer": "C",
            "correct": true
          },
          {
            "id_questions": 2128,
            "answer": "A",
            "correct": true
          },
          {
            "id_questions": 2146,
            "answer": "C",
            "correct": true
          },
          {
            "id_questions": 2076,
            "answer": "A",
            "correct": true
          },
          {
            "id_questions": 2067,
            "answer": "C",
            "correct": true
          },
          {
            "id_questions": 2185,
            "answer": "B",
            "correct": true
          },
          {
            "id_questions": 2200,
            "answer": "B",
            "correct": false
          },
          {
            "id_questions": 2105,
            "answer": "A",
            "correct": true
          },
          {
            "id_questions": 2066,
            "answer": "A",
            "correct": true
          },
          {
            "id_questions": 2175,
            "answer": "C",
            "correct": true
          },
          {
            "id_questions": 2140,
            "answer": "A",
            "correct": true
          },
          {
            "id_questions": 2112,
            "answer": "A",
            "correct": true
          },
          {
            "id_questions": 2138,
            "answer": "B",
            "correct": true
          },
          {
            "id_questions": 2121,
            "answer": "C",
            "correct": true
          },
          {
            "id_questions": 2101,
            "answer": "C",
            "correct": true
          },
          {
            "id_questions": 2111,
            "answer": "C",
            "correct": true
          },
          {
            "id_questions": 2189,
            "answer": "A",
            "correct": true
          },
          {
            "id_questions": 2142,
            "answer": "A",
            "correct": true
          },
          {
            "id_questions": 2188,
            "answer": "B",
            "correct": false
          },
          {
            "id_questions": 2082,
            "answer": "B",
            "correct": true
          },
          {
            "id_questions": 2080,
            "answer": "C",
            "correct": true
          },
          {
            "id_questions": 2197,
            "answer": "C",
            "correct": true
          },
          {
            "id_questions": 2171,
            "answer": "A",
            "correct": true
          },
          {
            "id_questions": 2154,
            "answer": "C",
            "correct": true
          },
          {
            "id_questions": 2155,
            "answer": "A",
            "correct": true
          },
          {
            "id_questions": 2135,
            "answer": "A",
            "correct": true
          },
          {
            "id_questions": 2070,
            "answer": "C",
            "correct": true
          },
          {
            "id_questions": 2168,
            "answer": "B",
            "correct": true
          },
          {
            "id_questions": 2129,
            "answer": "B",
            "correct": true
          },
          {
            "id_questions": 2079,
            "answer": "A",
            "correct": true
          },
          {
            "id_questions": 2086,
            "answer": "C",
            "correct": true
          },
          {
            "id_questions": 2167,
            "answer": "B",
            "correct": false
          },
          {
            "id_questions": 2183,
            "answer": "B",
            "correct": true
          },
          {
            "id_questions": 2088,
            "answer": "B",
            "correct": true
          },
          {
            "id_questions": 2095,
            "answer": "A",
            "correct": true
          },
          {
            "id_questions": 2204,
            "answer": "A",
            "correct": true
          },
          {
            "id_questions": 2116,
            "answer": "A",
            "correct": true
          },
          {
            "id_questions": 2081,
            "answer": "A",
            "correct": true
          },
          {
            "id_questions": 2074,
            "answer": "A",
            "correct": true
          },
          {
            "id_questions": 2162,
            "answer": "A",
            "correct": true
          },
          {
            "id_questions": 2113,
            "answer": "B",
            "correct": true
          },
          {
            "id_questions": 2104,
            "answer": "B",
            "correct": true
          },
          {
            "id_questions": 2201,
            "answer": "A",
            "correct": true
          },
          {
            "id_questions": 2071,
            "answer": "A",
            "correct": true
          },
          {
            "id_questions": 2131,
            "answer": "A",
            "correct": true
          },
          {
            "id_questions": 2174,
            "answer": "B",
            "correct": true
          },
          {
            "id_questions": 2107,
            "answer": "A",
            "correct": true
          },
          {
            "id_questions": 2090,
            "answer": "A",
            "correct": true
          },
          {
            "id_questions": 2068,
            "answer": "C",
            "correct": true
          },
          {
            "id_questions": 2099,
            "answer": "A",
            "correct": true
          },
          {
            "id_questions": 2072,
            "answer": "A",
            "correct": true
          },
          {
            "id_questions": 2178,
            "answer": "C",
            "correct": true
          },
          {
            "id_questions": 2110,
            "answer": "C",
            "correct": true
          },
          {
            "id_questions": 2109,
            "answer": "B",
            "correct": true
          },
          {
            "id_questions": 2177,
            "answer": "A",
            "correct": true
          },
          {
            "id_questions": 2182,
            "answer": "B",
            "correct": true
          },
          {
            "id_questions": 2179,
            "answer": "C",
            "correct": true
          },
          {
            "id_questions": 2191,
            "answer": "B",
            "correct": true
          },
          {
            "id_questions": 2137,
            "answer": "B",
            "correct": true
          },
          {
            "id_questions": 2203,
            "answer": "A",
            "correct": true
          },
          {
            "id_questions": 2083,
            "answer": "C",
            "correct": true
          },
          {
            "id_questions": 2092,
            "answer": "B",
            "correct": true
          },
          {
            "id_questions": 2186,
            "answer": "B",
            "correct": true
          },
          {
            "id_questions": 2075,
            "answer": "A",
            "correct": false
          },
          {
            "id_questions": 2094,
            "answer": "A",
            "correct": true
          },
          {
            "id_questions": 2169,
            "answer": "B",
            "correct": true
          },
          {
            "id_questions": 2139,
            "answer": "A",
            "correct": true
          },
          {
            "id_questions": 2176,
            "answer": "A",
            "correct": true
          },
          {
            "id_questions": 2078,
            "answer": "B",
            "correct": true
          },
          {
            "id_questions": 2073,
            "answer": "A",
            "correct": true
          },
          {
            "id_questions": 2163,
            "answer": "C",
            "correct": true
          },
          {
            "id_questions": 2062,
            "answer": "C",
            "correct": true
          },
          {
            "id_questions": 2103,
            "answer": "B",
            "correct": true
          },
          {
            "id_questions": 2124,
            "answer": "C",
            "correct": true
          },
          {
            "id_questions": 2127,
            "answer": "A",
            "correct": true
          },
          {
            "id_questions": 2134,
            "answer": "C",
            "correct": true
          },
          {
            "id_questions": 2194,
            "answer": "B",
            "correct": true
          },
          {
            "id_questions": 2148,
            "answer": "C",
            "correct": true
          },
          {
            "id_questions": 2158,
            "answer": "C",
            "correct": true
          },
          {
            "id_questions": 2069,
            "answer": "C",
            "correct": true
          },
          {
            "id_questions": 2136,
            "answer": "B",
            "correct": true
          },
          {
            "id_questions": 2150,
            "answer": "A",
            "correct": true
          },
          {
            "id_questions": 2199,
            "answer": "C",
            "correct": true
          },
          {
            "id_questions": 2089,
            "answer": "A",
            "correct": true
          },
          {
            "id_questions": 2192,
            "answer": "C",
            "correct": true
          }
        ],
        "correct": 136,
        "wrong": 7,
        "type": "quiz"
      },
      {
        "data": "2025-06-17T16:21:40.128Z",
        "categories": [
          "Egzamin 2021"
        ],
        "list": [
          {
            "id_questions": 2196,
            "answer": "B",
            "correct": false
          },
          {
            "id_questions": 2144,
            "answer": "A",
            "correct": true
          },
          {
            "id_questions": 2087,
            "answer": "B",
            "correct": true
          },
          {
            "id_questions": 2200,
            "answer": "A",
            "correct": true
          },
          {
            "id_questions": 2188,
            "answer": "B",
            "correct": false
          },
          {
            "id_questions": 2167,
            "answer": "C",
            "correct": true
          },
          {
            "id_questions": 2075,
            "answer": "B",
            "correct": false
          }
        ],
        "correct": 4,
        "wrong": 3,
        "type": "Quiz - poprawa błędów"
      },
      {
        "data": "2025-06-17T16:22:11.298Z",
        "categories": [
          "Egzamin 2021"
        ],
        "list": [
          {
            "id_questions": 2196,
            "answer": "C",
            "correct": true
          },
          {
            "id_questions": 2188,
            "answer": "A",
            "correct": true
          },
          {
            "id_questions": 2075,
            "answer": "C",
            "correct": true
          }
        ],
        "correct": 3,
        "wrong": 0,
        "type": "Quiz - poprawa błędów"
      }
    ]
  }
]